program/__init__.py
program-0.0.4.dist-info/LICENSE
program-0.0.4.dist-info/METADATA
program-0.0.4.dist-info/WHEEL
program-0.0.4.dist-info/top_level.txt
program-0.0.4.dist-info/RECORD
